LICENSE
recipe_cli/__init__.py
recipe_cli-0.1.3.dist-info/entry_points.txt
recipe_cli-0.1.3.dist-info/LICENSE
recipe_cli-0.1.3.dist-info/WHEEL
recipe_cli-0.1.3.dist-info/METADATA
recipe_cli-0.1.3.dist-info/RECORD
